README.md
setup.py
pulumi_materialize/__init__.py
pulumi_materialize/_inputs.py
pulumi_materialize/_utilities.py
pulumi_materialize/app_password.py
pulumi_materialize/cloud_region.py
pulumi_materialize/cluster.py
pulumi_materialize/cluster_replica.py
pulumi_materialize/connection_aws.py
pulumi_materialize/connection_aws_privatelink.py
pulumi_materialize/connection_confluent_schema_registry.py
pulumi_materialize/connection_kafka.py
pulumi_materialize/connection_mysql.py
pulumi_materialize/connection_postgres.py
pulumi_materialize/connection_sqlserver.py
pulumi_materialize/connection_ssh_tunnel.py
pulumi_materialize/database.py
pulumi_materialize/get_cluster_replicas.py
pulumi_materialize/get_clusters.py
pulumi_materialize/get_connections.py
pulumi_materialize/get_current_cluster.py
pulumi_materialize/get_current_database.py
pulumi_materialize/get_databases.py
pulumi_materialize/get_egress_ips.py
pulumi_materialize/get_indexes.py
pulumi_materialize/get_materialized_views.py
pulumi_materialize/get_network_policies.py
pulumi_materialize/get_roles.py
pulumi_materialize/get_schemas.py
pulumi_materialize/get_scim_configs.py
pulumi_materialize/get_scim_groups.py
pulumi_materialize/get_secrets.py
pulumi_materialize/get_sinks.py
pulumi_materialize/get_sources.py
pulumi_materialize/get_sso_config.py
pulumi_materialize/get_system_parameters.py
pulumi_materialize/get_tables.py
pulumi_materialize/get_types.py
pulumi_materialize/get_users.py
pulumi_materialize/get_views.py
pulumi_materialize/grant_cluster.py
pulumi_materialize/grant_cluster_default_privilege.py
pulumi_materialize/grant_connection.py
pulumi_materialize/grant_connection_default_privilege.py
pulumi_materialize/grant_database.py
pulumi_materialize/grant_database_default_privilege.py
pulumi_materialize/grant_materialized_view.py
pulumi_materialize/grant_role.py
pulumi_materialize/grant_schema.py
pulumi_materialize/grant_schema_default_privilege.py
pulumi_materialize/grant_secret.py
pulumi_materialize.egg-info/PKG-INFO
pulumi_materialize.egg-info/SOURCES.txt
pulumi_materialize.egg-info/dependency_links.txt
pulumi_materialize.egg-info/not-zip-safe
pulumi_materialize.egg-info/requires.txt
pulumi_materialize.egg-info/top_level.txt
