Metadata-Version: 2.1
Name: pulumi-materialize
Version: 0.4.1
Summary: A Pulumi package for creating and managing materialize cloud resources.
Home-page: https://github.com/MaterializeInc/terraform-provider-materialize
License: Apache-2.0
Project-URL: Repository, https://github.com/MaterializeInc/terraform-provider-materialize
Keywords: pulumi materialize category/cloud
Requires-Python: >=3.9
